lucidshark/__init__.py
lucidshark/bootstrap/__init__.py
lucidshark/bootstrap/paths.py
lucidshark/bootstrap/platform.py
lucidshark/bootstrap/validation.py
lucidshark/bootstrap/versions.py
lucidshark/cli/__init__.py
lucidshark/cli/__main__.py
lucidshark/cli/arguments.py
lucidshark/cli/config_bridge.py
lucidshark/cli/exit_codes.py
lucidshark/cli/runner.py
lucidshark/cli/commands/__init__.py
lucidshark/cli/commands/autoconfigure.py
lucidshark/cli/commands/help.py
lucidshark/cli/commands/init.py
lucidshark/cli/commands/list_scanners.py
lucidshark/cli/commands/scan.py
lucidshark/cli/commands/serve.py
lucidshark/cli/commands/status.py
lucidshark/cli/commands/validate.py
lucidshark/config/__init__.py
lucidshark/config/ignore.py
lucidshark/config/loader.py
lucidshark/config/models.py
lucidshark/config/validation.py
lucidshark/core/__init__.py
lucidshark/core/domain_runner.py
lucidshark/core/git.py
lucidshark/core/logging.py
lucidshark/core/models.py
lucidshark/core/paths.py
lucidshark/core/streaming.py
lucidshark/core/subprocess_runner.py
lucidshark/detection/__init__.py
lucidshark/detection/detector.py
lucidshark/detection/frameworks.py
lucidshark/detection/languages.py
lucidshark/detection/tools.py
lucidshark/generation/__init__.py
lucidshark/generation/config_generator.py
lucidshark/generation/package_installer.py
lucidshark/mcp/__init__.py
lucidshark/mcp/formatter.py
lucidshark/mcp/server.py
lucidshark/mcp/tools.py
lucidshark/mcp/watcher.py
lucidshark/pipeline/__init__.py
lucidshark/pipeline/executor.py
lucidshark/pipeline/parallel.py
lucidshark/plugins/__init__.py
lucidshark/plugins/discovery.py
lucidshark/plugins/coverage/__init__.py
lucidshark/plugins/coverage/base.py
lucidshark/plugins/coverage/coverage_py.py
lucidshark/plugins/coverage/istanbul.py
lucidshark/plugins/duplication/__init__.py
lucidshark/plugins/duplication/base.py
lucidshark/plugins/duplication/duplo.py
lucidshark/plugins/enrichers/__init__.py
lucidshark/plugins/enrichers/base.py
lucidshark-0.5.17.dist-info/licenses/LICENSE
lucidshark-0.5.17.dist-info/METADATA
lucidshark-0.5.17.dist-info/WHEEL
lucidshark-0.5.17.dist-info/entry_points.txt
lucidshark-0.5.17.dist-info/top_level.txt
lucidshark-0.5.17.dist-info/RECORD
